baidu_translate/__init__.py
baidu_translate/api.py
baidu_translate/domain.py
baidu_translate/errors.py
baidu_translate/languages.py
baidu_translate/models.py
baidu_translate/sign.py
baidu_translate/utils.py
baidu_translate_api-1.0.0.dist-info/LICENSE
baidu_translate_api-1.0.0.dist-info/METADATA
baidu_translate_api-1.0.0.dist-info/WHEEL
baidu_translate_api-1.0.0.dist-info/top_level.txt
baidu_translate_api-1.0.0.dist-info/RECORD
