Metadata-Version: 2.1
Name: baidu-translate-api
Version: 1.0.0
Summary: 一个免费, 高效, 简洁百度翻译接口
Home-page: https://github.com/tq-xyy/baidu-translate/
Author: tq_xyy
Author-email: m17097231932@163.com
License: Unlicense
Project-URL: Documentation, https://github.com/tq-xyy/baidu-translate#readme
Project-URL: Code, https://github.com/tq-xyy/baidu-translate
Project-URL: Issue tracker, https://github.com/tq-xyy/baidu-translate/issues
License-File: LICENSE
Requires-Dist: httpx
Requires-Dist: pycryptodome
